facespace/__init__.py
facespace/facespace_client.py
facespace-0.1.2.dist-info/LICENSE.txt
facespace-0.1.2.dist-info/METADATA
facespace-0.1.2.dist-info/WHEEL
facespace-0.1.2.dist-info/top_level.txt
facespace-0.1.2.dist-info/RECORD
