Metadata-Version: 2.1
Name: facespace
Version: 0.1.2
Summary: A client for FaceSpace API services
Home-page: https://vision.automa.one
Author: Automa
Author-email: facespace@automa.one
Classifier: Development Status :: 3 - Alpha
Classifier: Intended Audience :: Developers
Classifier: Intended Audience :: Information Technology
Classifier: Intended Audience :: Science/Research
Classifier: License :: OSI Approved :: MIT License
Classifier: Programming Language :: Python :: 3
Classifier: Programming Language :: Python :: 3.8
Classifier: Programming Language :: Python :: 3.9
Classifier: Programming Language :: Python :: 3.10
Classifier: Operating System :: OS Independent
Requires-Python: >=3.8
License-File: LICENSE.txt
Requires-Dist: requests
Requires-Dist: python-dateutil
Requires-Dist: urllib3
